django_tibero/__init__.py
django_tibero/base.py
django_tibero/client.py
django_tibero/creation.py
django_tibero/features.py
django_tibero/functions.py
django_tibero/introspection.py
django_tibero/operations.py
django_tibero/schema.py
django_tibero/utils.py
django_tibero/validation.py
django_tibero-0.0.2.dist-info/LICENSE.md
django_tibero-0.0.2.dist-info/METADATA
django_tibero-0.0.2.dist-info/WHEEL
django_tibero-0.0.2.dist-info/top_level.txt
django_tibero-0.0.2.dist-info/RECORD
