Metadata-Version: 2.2
Name: django-tibero
Version: 0.0.2
Summary: Django Tibero Backend
Home-page: https://github.com/TiberoClient/django-tibero
Author: Yeongbae Jeon
Author-email: ybjeon01@naver.com
License: BSD
Project-URL: Documentation, https://github.com/TiberoClient/django-tibero/wiki
Project-URL: Source, https://github.com/TiberoClient/django-tibero
Project-URL: Tracker, https://github.com/TiberoClient/django-tibero/issues
Keywords: Django,Tibero
Classifier: Development Status :: 3 - Alpha
Classifier: Intended Audience :: Developers
Classifier: License :: OSI Approved :: BSD License
Classifier: Operating System :: OS Independent
Classifier: Programming Language :: Python
Classifier: Programming Language :: Python :: 3
Classifier: Programming Language :: Python :: 3.10
Classifier: Programming Language :: Python :: 3.11
Classifier: Programming Language :: Python :: 3.12
Classifier: Programming Language :: Python :: 3.13
Classifier: Programming Language :: Python :: Implementation :: CPython
Classifier: Framework :: Django :: 5.1
Classifier: Topic :: Database :: Front-Ends
Requires-Python: >=3.10
License-File: LICENSE.md
Requires-Dist: django<5.2,>=5.1
Requires-Dist: pyodbc>=5.0
Provides-Extra: dev
Requires-Dist: ruff; extra == "dev"
Requires-Dist: mypy; extra == "dev"
Requires-Dist: setuptools; extra == "dev"
Requires-Dist: twine; extra == "dev"
